pdiffutils/__init__.py
pdiffutils/pdiffutils.py
pdiffutils/split_on_zero.py
pdiffutils-0.0.3.dist-info/AUTHORS.rst
pdiffutils-0.0.3.dist-info/LICENSE
pdiffutils-0.0.3.dist-info/METADATA
pdiffutils-0.0.3.dist-info/WHEEL
pdiffutils-0.0.3.dist-info/top_level.txt
pdiffutils-0.0.3.dist-info/RECORD
